{"_id":{"$oid":"637f3ac4bd664a0327f6bfee"},"personalInfo":{"firstName":"Jan","secondName":null,"lastName":"Nowak","birthDate":{"$date":"2000-02-12T00:00:00Z"},"address":{"street":"Limanowska","buildingNumber":"21","flatNumber":"37","postalCode":"33-300","city":"Nowy Sącz"}},"fieldOfStudies":[{"name":"Mechanika","studiesType":["stacjonarne","I stopnia"],"current":true,"finished":false}],"startedStuding":{"$date":"2020-10-01T00:00:00Z"},"currentSemestr":5,"studentStatus":{"status":"Aktywny","special":"Warunek"},"subjects":[{"name":"Fizyka","semestr":1,"isFinished":false,"ects":4,"mark":4.5},{"name":"Mechanika Płynów","semestr":4,"isFinished":false,"ects":3,"mark":2}],"studentEmail":"jan.nowak@student.pk.edu.pl","indexNumber":132839,"contactEmail":"jan.nowak@gmail.com"}
{"_id":{"$oid":"637f3ac4bd664a0327f6bfef"},"personalInfo":{"firstName":"Konrad","secondName":"Bogdan","lastName":"Kazimierczak","birthDate":{"$date":"1999-04-01T00:00:00Z"},"address":{"street":"Nowa","buildingNumber":2,"postalCode":"23-333","city":"Hutki Kanki"}},"fieldOfStudies":[{"name":"Informatyka Stosowana","studiesType":["stacjonarne","I stopnia"],"current":true,"finished":false}],"startedStuding":{"$date":"2021-10-01T00:00:00Z"},"currentSemestr":3,"studentStatus":{"status":"Aktywny"},"subjects":[{"name":"Programowanie obiektowe","semestr":2,"isFinished":false,"ects":4,"mark":3},{"name":"Front-End","semestr":4,"isFinished":false,"ects":3,"mark":2}],"studentEmail":"bogdan.kazimierczak@student.pk.edu.pl","indexNumber":132839,"contactEmail":"kbk@gmail.com"}
{"_id":{"$oid":"637f3ac4bd664a0327f6bff1"},"personalInfo":{"firstName":"Zenon","secondName":"Adam","lastName":"Kiler","birthDate":{"$date":"1995-10-09T00:00:00Z"},"address":{"street":"Warszawska","buildingNumber":102,"postalCode":"41-300","city":"Zielone Górki"}},"fieldOfStudies":[{"name":"Informatyka Stosowana","studiesType":["stacjonarne","I stopnia"],"current":false,"finished":false}],"startedStuding":{"$date":"2021-10-01T00:00:00Z"},"currentSemestr":7,"studentStatus":{"status":"Aktywny"},"subjects":[{"name":"Programowanie obiektowe","semestr":2,"isFinished":false,"ects":4,"mark":4},{"name":"Front-End","semestr":4,"isFinished":false,"ects":3,"mark":2},{"name":"Analiza obrazu","semestr":5,"isFinished":false,"ects":4,"mark":2}],"studentEmail":"zenon.kiler@student.pk.edu.pl","indexNumber":132839,"contactEmail":"kilerz@o2.pl"}
{"_id":{"$oid":"637f3ac4bd664a0327f6bff0"},"personalInfo":{"firstName":"Aleksandra","lastName":"Słowik","birthDate":{"$date":"1998-07-22T00:00:00Z"},"address":{"street":"Czeska","buildingNumber":"12","flatNumber":"43","postalCode":"33-300","city":"Nowy Sącz"}},"fieldOfStudies":[{"name":"Geoinformatyka","studiesType":["stacjonarne","I stopnia"],"department":"WIŚiE","current":true,"finished":false},{"name":"Inżynieria Środowiska","studiesType":["stacjonarne","I stopnia"],"department":"WIŚiE","current":false,"finished":true,"finalMark":4.5,"finishDate":{"$date":"2021-06-30T00:00:00Z"}}],"startedStuding":{"$date":"2018-10-01T00:00:00Z"},"currentSemestr":5,"studentStatus":{"status":"Aktywny"},"subjects":[{"name":"Geologia","semestr":2,"isFinished":true,"ects":1,"mark":5},{"name":"Bazy Danych","semestr":4,"isFinished":true,"ects":3,"mark":4},{"name":"Bazy Danych NoSQL","semestr":5,"isFinished":false,"ects":4}],"studentEmail":"aleksandra.słowik@student.pk.edu.pl","indexNumber":132839,"contactEmail":"asłowik@hotmail.com"}
{"_id":{"$oid":"6452ad11cd82b8486157c316"},"personalInfo":{"firstName":"Krystian","secondName":"Jan","lastName":"Dutka","birthDate":{"$date":"2000-06-09T00:00:00Z"},"address":{"street":"Centralna","buildingNumer":34,"flatNumber":45,"postalCode":"31-586","city":"Kraków"}},"fieldOfStudies":[{"name":"Informatyka stosowana","studiesType":["stacjonarne","II stopnia"],"current":true,"finished":false},{"name":"Informatyka stosowana","studiesType":["stacjonarne","I stopnia"],"current":false,"finished":true}],"startedStuding":{"$date":"2019-10-01T00:00:00Z"},"currentSemestr":8,"studentStatus":{"status":"Aktywny"},"subjects":[{"name":"Bazy danych II","semester":1,"isFinished":false,"ects":2,"mark":5},{"name":"Algorytmy decyzyjne","semester":1,"isFinished":false,"ects":2,"mark":5},{"name":"Wieloplatformowe aplikacje mobilne","semester":1,"isFinished":false,"ects":4,"mark":4},{"name":"Sieci komputerowe II","semester":1,"isFinished":false,"ects":4,"mark":5}],"studentEmail":"krystian.dutka@student.pk.edu.pl","indexNumber":132839,"contactEmail":"krystian.dutka@gamil.com"}